ovs_dbg/__init__.py
ovs_dbg/_version.py
ovs_dbg/logs.py
ovs_dbg/ofparse/__init__.py
ovs_dbg/ofparse/console.py
ovs_dbg/ofparse/dp.py
ovs_dbg/ofparse/dp_graph.py
ovs_dbg/ofparse/dp_tree.py
ovs_dbg/ofparse/format.py
ovs_dbg/ofparse/html.py
ovs_dbg/ofparse/main.py
ovs_dbg/ofparse/ofp.py
ovs_dbg/ofparse/ofp_logic.py
ovs_dbg/ofparse/process.py
ovs_dbg/ofparse/etc/ofparse.conf
ovs_dbg/vendor/ovs/__init__.py
ovs_dbg/vendor/ovs/daemon.py
ovs_dbg/vendor/ovs/dirs.py
ovs_dbg/vendor/ovs/fatal_signal.py
ovs_dbg/vendor/ovs/fcntl_win.py
ovs_dbg/vendor/ovs/json.py
ovs_dbg/vendor/ovs/jsonrpc.py
ovs_dbg/vendor/ovs/ovsuuid.py
ovs_dbg/vendor/ovs/poller.py
ovs_dbg/vendor/ovs/process.py
ovs_dbg/vendor/ovs/reconnect.py
ovs_dbg/vendor/ovs/socket_util.py
ovs_dbg/vendor/ovs/stream.py
ovs_dbg/vendor/ovs/timeval.py
ovs_dbg/vendor/ovs/util.py
ovs_dbg/vendor/ovs/version.py
ovs_dbg/vendor/ovs/vlog.py
ovs_dbg/vendor/ovs/winutils.py
ovs_dbg/vendor/ovs/flow/__init__.py
ovs_dbg/vendor/ovs/flow/decoders.py
ovs_dbg/vendor/ovs/flow/filter.py
ovs_dbg/vendor/ovs/flow/flow.py
ovs_dbg/vendor/ovs/flow/kv.py
ovs_dbg/vendor/ovs/flow/list.py
ovs_dbg/vendor/ovs/flow/odp.py
ovs_dbg/vendor/ovs/flow/ofp.py
ovs_dbg/vendor/ovs/flow/ofp_act.py
ovs_dbg/vendor/ovs/flow/ofp_fields.py
ovs_dbg-0.0.18.data/data/etc/ofparse.conf
ovs_dbg-0.0.18.data/data/extras/ovs-lgrep.completion.bash
ovs_dbg-0.0.18.data/data/extras/ovs-offline.completion.bash
ovs_dbg-0.0.18.data/data/extras/ovs-ofparse.completion.bash
ovs_dbg-0.0.18.data/scripts/ovs-dbg-complete
ovs_dbg-0.0.18.data/scripts/ovs-lgrep
ovs_dbg-0.0.18.data/scripts/ovs-offline
ovs_dbg-0.0.18.data/scripts/ovs-ofparse
ovs_dbg-0.0.18.dist-info/LICENSE
ovs_dbg-0.0.18.dist-info/METADATA
ovs_dbg-0.0.18.dist-info/WHEEL
ovs_dbg-0.0.18.dist-info/top_level.txt
ovs_dbg-0.0.18.dist-info/RECORD
